tactigon_speech/__init__.py
tactigon_speech/models.py
tactigon_speech/hal/Tactigon_Audio.py
tactigon_speech/hal/__init__.py
tactigon_speech/middleware/__init__.py
tactigon_speech-4.0.5.dist-info/LICENSE
tactigon_speech-4.0.5.dist-info/METADATA
tactigon_speech-4.0.5.dist-info/WHEEL
tactigon_speech-4.0.5.dist-info/top_level.txt
tactigon_speech-4.0.5.dist-info/RECORD
