Metadata-Version: 2.1
Name: tactigon-speech
Version: 4.0.5
Summary: Tactigon Gear speech to transcribe text into commands
Author-email: "Next Industries s.r.l" <info@nextind.eu>
Project-URL: Homepage, https://nextind.eu
Classifier: Programming Language :: Python :: 3
Classifier: License :: OSI Approved :: MIT License
Classifier: Operating System :: OS Independent
Requires-Python: >=3.8
License-File: LICENSE
Requires-Dist: tactigon-gear >=4.1.0
Requires-Dist: deepspeech-tflite ==0.9.3
Requires-Dist: PyAudio ==0.2.13
Requires-Dist: webrtcvad ==2.0.10
